MANIFEST.in
README
metadata.py
setup.py
/home/varmaa/pydermonkey/setup.py
docs/rendered/genindex.html
docs/rendered/index.html
docs/rendered/modindex.html
docs/rendered/pydermonkey.html
docs/rendered/search.html
docs/rendered/searchindex.js
docs/rendered/_sources/index.txt
docs/rendered/_sources/pydermonkey.txt
docs/rendered/_static/basic.css
docs/rendered/_static/default.css
docs/rendered/_static/doctools.js
docs/rendered/_static/file.png
docs/rendered/_static/jquery.js
docs/rendered/_static/minus.png
docs/rendered/_static/plus.png
docs/rendered/_static/pygments.css
docs/rendered/_static/searchtools.js
docs/src/conf.py
docs/src/index.txt
docs/src/pydermonkey.txt
pydermonkey.egg-info/PKG-INFO
pydermonkey.egg-info/SOURCES.txt
pydermonkey.egg-info/dependency_links.txt
pydermonkey.egg-info/native_libs.txt
pydermonkey.egg-info/top_level.txt
python-modules/paver/__init__.py
python-modules/paver/defaults.py
python-modules/paver/easy.py
python-modules/paver/misctasks.py
python-modules/paver/options.py
python-modules/paver/path.py
python-modules/paver/path25.py
python-modules/paver/release.py
python-modules/paver/setuputils.py
python-modules/paver/tasks.py
src/context.cpp
src/context.h
src/function.cpp
src/function.h
src/object.cpp
src/object.h
src/pydermonkey.cpp
src/runtime.cpp
src/runtime.h
src/script.cpp
src/script.h
src/undefined.cpp
src/undefined.h
src/utils.cpp
src/utils.h
test/test_pydermonkey.py
