Metadata-Version: 1.0
Name: pydermonkey
Version: 0.0.6
Summary: Access the SpiderMonkey JavaScript engine from Python
Home-page: http://code.google.com/p/pydermonkey/
Author: Atul Varma
Author-email: atul@mozilla.com
License: UNKNOWN
Platform: UNKNOWN
Classifier: Development Status :: 3 - Alpha
Classifier: Intended Audience :: Developers
Classifier: License :: OSI Approved :: Mozilla Public License 1.1 (MPL 1.1)
Classifier: Programming Language :: Python
Classifier: Programming Language :: JavaScript
Classifier: Topic :: Software Development :: Interpreters
